buttontoled/buttontoled.v
module buttontoled (i_sw, o_led);
		
		input  wire  i_sw ;
		output wire  o_led;
		
		assign o_led =  i_sw ;
		
endmodule

buttontoled/buttontoled_tb.v
`timescale 1ns/1ps
module buttontoled_tb(output wire o_led);
    reg i_sw;
    buttontoled UUT (.i_sw(i_sw), .o_led(o_led));
    always@(posedge i_sw)// i would asume this is always statment is
    begin
       assign i_sw = 1;
       #10
       assign i_sw = 0 ;
    end     
    initial begin
        $dumpfile("buttontoled_tb.vcd");
        $dumpvars(0,buttontoled_tb);
    end
 
 endmodule

buttontoled/buttontoled_tb.vcd
$date
	Thu May 14 17:43:38 2020
$end
$version
	Icarus Verilog
$end
$timescale
	100ps
$end
$scope module buttontoled_tb $end
$var wire 1 ! o_led $end
$var reg 1 " i_sw $end
$scope module u1 $end
$var wire 1 " i_sw $end
$var wire 1 ! o_led $end
$upscope $end
$upscope $end
$enddefinitions $end
#0
$dumpvars
1"
1!
$end
#1000
0!
0"
#2000
1!
1"
#3000
0!
0"
#4000
1!
1"
#5000
0!
0"
#6000
1!
1"
#7000
0!
0"
#8000
1!
1"
#9000
0!
0"
