buttontoled/buttontoled.v
module buttontoled (i_sw, o_led);
		
		input  wire  i_sw ;
		output wire  o_led;
		
		assign o_led =!  i_sw ;
		
endmodule

buttontoled/buttontoled_tb.v
//`default_nettype none
`timescale 1ns / 100ps


module buttontoled_tb () ;

//Declarations of the wires
reg i_sw  ; 
wire o_led ;

// instantiate the DUT
buttontoled u1(
				.i_sw (i_sw),
				.o_led (o_led)				



			   );		
	


initial begin 
	$dumpfile ("buttontoled_tb.vcd");
	$dumpvars (0,buttontoled_tb    );
end 
initial begin 
	i_sw = 1 ;
	#100
	i_sw = 0 ;
	#100;
	i_sw = 1 ;
	#100
	i_sw = 0 ;
	#100;
	i_sw = 1 ;
	#100
	i_sw = 0 ;
	#100;
	i_sw = 1 ;
	#100
	i_sw = 0 ;
	#100;
	i_sw = 1 ;
	#100
	i_sw = 0 ;
	#100;
end 	
endmodule

buttontoled/buttontoled_tb.vcd
$date
	Wed May 13 21:34:14 2020
$end
$version
	Icarus Verilog
$end
$timescale
	100ps
$end
$scope module buttontoled_tb $end
$var wire 1 ! o_led $end
$var reg 1 " i_sw $end
$scope module u1 $end
$var wire 1 " i_sw $end
$var wire 1 ! o_led $end
$upscope $end
$upscope $end
$enddefinitions $end
#0
$dumpvars
1"
0!
$end
#1000
1!
0"
#2000
0!
1"
#3000
1!
0"
#4000
0!
1"
#5000
1!
0"
#6000
0!
1"
#7000
1!
0"
#8000
0!
1"
#9000
1!
0"
