buttoncounter/buttoncounter.v
module buttoncounter (button, display,clk);
	   
	  input wire  button   ;
	  input wire  clk      ;
	  output reg [6:0 ] display;
	  reg [14:0] counter;
    always @(posedge clk)
	  	begin
	   		if(button == 1)
				begin
		 			counter <= counter + 1'b1 ;
				end
			if (counter==15)
				begin
					counter <= 1'b0;
				end 
	    	
		
		case(counter)
			
	   			16'h0	  : display <= 7'b1000000 ;//0
				16'h1	  : display <= 7'b1111001 ;//1
				16'h2	  : display <= 7'b0100100 ;//2
				16'h3	  : display <= 7'b0110000 ;//3
				16'h4	  : display <= 7'b0011001 ;//4
				16'h5	  : display <= 7'b0010010 ;//5
				16'h6	  : display <= 7'b0000010 ;//6
			 	16'h7	  : display <= 7'b1111000 ;//7
			 	16'h9	  : display <= 7'b0010000 ;//9
				16'hA	  : display <= 7'b0001000 ;//10
			 	16'hB	  : display <= 7'b0000011 ;//11
			 	16'hC     : display <= 7'b1000110 ;//12
			 	16'hD     : display <= 7'b0100001 ;//13
			 	16'hE     : display <= 7'b0000110 ;//14
			 	16'hF	  : display <= 7'b0001110 ;//15
	    	 	default   : display <= 7'b1111111 ;// blank 
		    
		endcase
	end
endmodule

buttoncounter/buttoncounter_TB.v
  `timescale 1ns / 100ps

module buttoncounter_tb;
reg button;
reg clk;
wire  [6:0 ] display;

integer i ;
integer j ;

buttoncounter u1 
(
    .clk(clk),
    .button (button),
    .display(display)
);

initial begin
    $dumpfile ("buttoncounter_tb.vcd");
    $dumpvars ( 0,buttoncounter_tb   );
end
initial begin
        clk = 0;
        for( i = 0; i < 10; i = i + 1)
        begin
            #82 clk = ~ clk;
        end
        for( j = 0 ; j < 10 ; j = j + 1)
        begin
            button = ~ button;
        end

end
endmodule

buttoncounter/buttoncounter_tb.vcd
$date
	Wed Jun 24 22:02:54 2020
$end
$version
	Icarus Verilog
$end
$timescale
	100ps
$end
$scope module buttoncounter_tb $end
$var wire 7 ! display [6:0] $end
$var reg 1 " button $end
$var reg 1 # clk $end
$var integer 32 $ i [31:0] $end
$var integer 32 % j [31:0] $end
$scope module u1 $end
$var wire 1 " button $end
$var wire 1 # clk $end
$var reg 15 & counter [14:0] $end
$var reg 7 ' display [6:0] $end
$upscope $end
$upscope $end
$enddefinitions $end
#0
$dumpvars
bx '
bx &
bx %
b0 $
0#
x"
bx !
$end
#820
b1111111 !
b1111111 '
b1 $
1#
#1640
b10 $
0#
#2460
b11 $
1#
#3280
b100 $
0#
#4100
b101 $
1#
#4920
b110 $
0#
#5740
b111 $
1#
#6560
b1000 $
0#
#7380
b1001 $
1#
#8200
b1010 %
b1010 $
0#
